<PAMDataset>
  <Metadata domain="IMAGE_STRUCTURE">
    <MDI key="COMPRESSION">JPEG</MDI>
    <MDI key="INTERLEAVE">PIXEL</MDI>
    <MDI key="SOURCE_COLOR_SPACE">YCbCr</MDI>
  </Metadata>
  <PAMRasterBand band="1">
    <Metadata domain="IMAGE_STRUCTURE">
      <MDI key="COMPRESSION">JPEG</MDI>
    </Metadata>
    <Metadata>
      <MDI key="STATISTICS_APPROXIMATE">YES</MDI>
      <MDI key="STATISTICS_MAXIMUM">235</MDI>
      <MDI key="STATISTICS_MEAN">71.293306966839</MDI>
      <MDI key="STATISTICS_MINIMUM">2</MDI>
      <MDI key="STATISTICS_STDDEV">58.189208398684</MDI>
      <MDI key="STATISTICS_VALID_PERCENT">100</MDI>
    </Metadata>
  </PAMRasterBand>
  <PAMRasterBand band="2">
    <Metadata domain="IMAGE_STRUCTURE">
      <MDI key="COMPRESSION">JPEG</MDI>
    </Metadata>
    <Metadata>
      <MDI key="STATISTICS_APPROXIMATE">YES</MDI>
      <MDI key="STATISTICS_MAXIMUM">232</MDI>
      <MDI key="STATISTICS_MEAN">78.372984484332</MDI>
      <MDI key="STATISTICS_MINIMUM">7</MDI>
      <MDI key="STATISTICS_STDDEV">48.352571446689</MDI>
      <MDI key="STATISTICS_VALID_PERCENT">100</MDI>
    </Metadata>
  </PAMRasterBand>
  <PAMRasterBand band="3">
    <Metadata domain="IMAGE_STRUCTURE">
      <MDI key="COMPRESSION">JPEG</MDI>
    </Metadata>
    <Metadata>
      <MDI key="STATISTICS_APPROXIMATE">YES</MDI>
      <MDI key="STATISTICS_MAXIMUM">232</MDI>
      <MDI key="STATISTICS_MEAN">61.94832674171</MDI>
      <MDI key="STATISTICS_MINIMUM">0</MDI>
      <MDI key="STATISTICS_STDDEV">40.34399382729</MDI>
      <MDI key="STATISTICS_VALID_PERCENT">100</MDI>
    </Metadata>
  </PAMRasterBand>
</PAMDataset>
